collections_extension/__init__.py
collections_extension/exception.py
collections_extension/native.py
collections_extension/py.typed
collections_extension/sqlalchemy/__init__.py
collections_extension/sqlalchemy/model.py
collections_extension/sqlalchemy/schema.py
collections_extension-0.5.0.dist-info/LICENSE.txt
collections_extension-0.5.0.dist-info/WHEEL
collections_extension-0.5.0.dist-info/METADATA
collections_extension-0.5.0.dist-info/RECORD
