Metadata-Version: 2.1
Name: collections-extension
Version: 0.5.0
Summary: Extra core collecions package additionals.
Home-page: https://bitbucket.org/bfg-soft/collections_extension
License: MIT
Author: BFG-Soft LLC
Author-email: info@bfg-soft.ru
Maintainer: Vladimir V. Pivovarov
Maintainer-email: pvv@bfg-soft.ru
Requires-Python: >=3.8,<4.0
Classifier: Development Status :: 4 - Beta
Classifier: Intended Audience :: Developers
Classifier: License :: OSI Approved :: MIT License
Classifier: Programming Language :: Python :: 3
Classifier: Programming Language :: Python :: 3.10
Classifier: Programming Language :: Python :: 3.8
Classifier: Programming Language :: Python :: 3.9
Classifier: Topic :: Software Development :: Libraries
Classifier: Typing :: Typed
Provides-Extra: marshmallow-sqlalchemy
Provides-Extra: sqlalchemy
Requires-Dist: SQLAlchemy (>=1.4.0,<2.0.0); extra == "sqlalchemy" or extra == "marshmallow-sqlalchemy"
Requires-Dist: marshmallow (>=3.0.0,<4.0.0); extra == "marshmallow-sqlalchemy"
Requires-Dist: marshmallow-sqlalchemy (>=0.28.1,<0.29.0); extra == "marshmallow-sqlalchemy"
Project-URL: Repository, https://bitbucket.org/bfg-soft/collections_extension
